owasp_nest/__init__.py
owasp_nest/_version.py
owasp_nest/basesdk.py
owasp_nest/chapters.py
owasp_nest/committees.py
owasp_nest/community.py
owasp_nest/events.py
owasp_nest/httpclient.py
owasp_nest/issues.py
owasp_nest/milestones.py
owasp_nest/projects.py
owasp_nest/py.typed
owasp_nest/releases.py
owasp_nest/repositories.py
owasp_nest/sdk.py
owasp_nest/sdkconfiguration.py
owasp_nest/sponsors.py
owasp_nest/_hooks/__init__.py
owasp_nest/_hooks/sdkhooks.py
owasp_nest/_hooks/types.py
owasp_nest/models/__init__.py
owasp_nest/models/chapter.py
owasp_nest/models/chapterdetail.py
owasp_nest/models/chaptererror.py
owasp_nest/models/committee.py
owasp_nest/models/committeedetail.py
owasp_nest/models/committeeerror.py
owasp_nest/models/event.py
owasp_nest/models/eventdetail.py
owasp_nest/models/eventerror.py
owasp_nest/models/get_chapterop.py
owasp_nest/models/get_committeeop.py
owasp_nest/models/get_eventop.py
owasp_nest/models/get_issueop.py
owasp_nest/models/get_memberop.py
owasp_nest/models/get_milestoneop.py
owasp_nest/models/get_organizationop.py
owasp_nest/models/get_projectop.py
owasp_nest/models/get_releaseop.py
owasp_nest/models/get_repositoryop.py
owasp_nest/models/get_snapshotop.py
owasp_nest/models/get_sponsorop.py
owasp_nest/models/issue.py
owasp_nest/models/issuedetail.py
owasp_nest/models/issueerror.py
owasp_nest/models/leader.py
owasp_nest/models/list_chaptersop.py
owasp_nest/models/list_committeesop.py
owasp_nest/models/list_eventsop.py
owasp_nest/models/list_issuesop.py
owasp_nest/models/list_membersop.py
owasp_nest/models/list_milestonesop.py
owasp_nest/models/list_organizationsop.py
owasp_nest/models/list_projectsop.py
owasp_nest/models/list_releasesop.py
owasp_nest/models/list_repositoriesop.py
owasp_nest/models/list_snapshot_chaptersop.py
owasp_nest/models/list_snapshot_issuesop.py
owasp_nest/models/list_snapshot_membersop.py
owasp_nest/models/list_snapshot_projectsop.py
owasp_nest/models/list_snapshot_releasesop.py
owasp_nest/models/list_snapshotsop.py
owasp_nest-0.3.7.dist-info/licenses/LICENSE
owasp_nest-0.3.7.dist-info/METADATA
owasp_nest-0.3.7.dist-info/WHEEL
owasp_nest-0.3.7.dist-info/top_level.txt
owasp_nest-0.3.7.dist-info/RECORD
