Metadata-Version: 2.4
Name: owasp-nest
Version: 0.3.7
Summary: OWASP Nest Python SDK
Author: Arkadii Yakovets
Project-URL: repository, https://github.com/OWASP/nest-sdk-python.git
Requires-Python: >=3.9.2
License-File: LICENSE
Requires-Dist: httpcore>=1.0.9
Requires-Dist: httpx>=0.28.1
Requires-Dist: pydantic>=2.11.2
Dynamic: license-file
